{
  "id": "art-406",
  "title": "Contemporary Issues in Painting",
  "description": "Focused investigation into contemporary topics in painting, with connections made to traditional approaches. Formal concerns (color, space, light, composition) balanced with conceptual development. Topics may include, but are not limited to, the human figure, landscape, and technological influences. The Schedule of Classes will list topic selected. Total credit limited to 8 units. 3 lectures, 1 laboratory.",
  "units": "4",
  "prerequisites": "ART 309 or consent of instructor",
  "corequisites": null,
  "crnc": false
}