{
  "id": "bio-434",
  "title": "Environmental Physiology",
  "description": "Comparative physiological mechanisms involved in the regulation of oxygen uptake, water and ion balance, and temperature regulation in animals. Emphasis is placed on physiological adaptations which maintain or restore homeostasis in animals which are subjected to environmental changes. 3 lectures, 1 laboratory.",
  "units": "4",
  "prerequisites": "BIO 162, or graduate standing in Biological Sciences",
  "corequisites": null,
  "crnc": false
}