{
  "id": "bio-200",
  "title": "Special Problems For Undergrads",
  "description": "Individual investigation, research, studies or surveys of selected problems. Intended for lower division students in the Biological Sciences Department. Total credit limited to 4 units, with a maximum of 2 units per quarter. Credit does not apply to any concentration in the Biological Sciences Department. Credit/No Credit grading only. 1-2 laboratories.",
  "units": "1-2",
  "prerequisites": "Consent of department chair",
  "corequisites": null,
  "recommended": null,
  "ges": [],
  "crnc": true,
  "gwr": false,
  "uscp": false
}