{
  "id": "brae-324",
  "title": "Principles of Agricultural Electrification",
  "description": "Applications of DC/AC electricity in agriculture. National Electric Code regulations. The wiring of agricultural structures and electrical distribution. Series, parallel and series-parallel circuits, R-L-C circuits, electric motors, electronics. 3 lectures, 1 laboratory.",
  "units": "4",
  "prerequisites": "MATH 119, PHYS 121",
  "corequisites": null,
  "recommended": null,
  "ges": [],
  "crnc": false,
  "gwr": false,
  "uscp": false
}