{
  "id": "cpe-484",
  "title": "User-Centered Interface Design and Development",
  "description": "Introduction to the importance of user-centered principles in the design of good interfaces and effective human-computer interaction. Topics include: study of human characteristics affected by interface design, effective requirements data collection and analysis, user-centered approaches to software engineering, and evaluation of interface and interaction quality. 3 lectures, 1 laboratory. Crosslisted as CPE/CSC 484.",
  "units": "4",
  "prerequisites": "Junior standing and CSC/CPE 307 or CSC/CPE 308",
  "corequisites": null,
  "crnc": false
}