{
  "id": "enve-330",
  "title": "Environmental Quality Control",
  "description": "Application of scientific and engineering principles to control the development and use of air, water and land resources. Control of pollution of the environment. Disposal of wastes. Administrative and legal aspects. For non-Engineering majors. 4 lectures.",
  "units": "4",
  "prerequisites": "Completion of GE Area B and junior standing",
  "corequisites": null,
  "recommended": null,
  "ges": [],
  "crnc": false,
  "gwr": false,
  "uscp": false
}