{
  "id": "fsn-322",
  "title": "French Foods in French",
  "description": "Blend of French language, culture, food preparation techniques, and basic food chemistry and nutrition. Total immersion in language and cooking: preparation of French food while interacting in French with classmates and instructors, in lectures, discussion, and laboratory. 3 lectures, 1 laboratory. Crosslisted as FR/FSN 322.",
  "units": "4",
  "prerequisites": "FR 103 or consent of instructor",
  "corequisites": null,
  "recommended": null,
  "ges": [],
  "crnc": false,
  "gwr": false,
  "uscp": false
}