{
  "id": "gsa-546",
  "title": "Tax Research and Administrative Procedures",
  "description": "Research techniques applicable to tax issues including the communication of research results. Administrative procedures necessary for tax compliance with the various tax jurisdictions with primary emphasis on IRS practices. 2 seminars, 2 activities.",
  "units": "4",
  "prerequisites": "OCOB graduate standing or approval from the Associate Dean",
  "corequisites": null,
  "recommended": null,
  "ges": [],
  "crnc": false,
  "gwr": false,
  "uscp": false
}