{
  "id": "rpta-527",
  "title": "Leisure Behavior and Theory",
  "description": "Theories of recreation and leisure; conceptual and theoretical foundations of leisure; the role of leisure behavior in modern day society. The Schedule of Classes will list topic selected. Constructs that contribute to contemporary understanding of leisure behavior. Connection of theories to individual research. Total credit limited to 8 units. 4 lectures.",
  "units": "4",
  "prerequisites": "Graduate standing",
  "corequisites": null,
  "recommended": null,
  "ges": [],
  "crnc": false,
  "gwr": false,
  "uscp": false
}