{
  "id": "univ-491",
  "title": "Appropriate Technology for the World's People: Development",
  "description": "A broad overview of international development and appropriate design for sustainability. Besides traditional classroom work, students work in teams to address problems with technical solutions. Collaboration with mentors from the university, private sector, and nonprofits serves to provide diverse background and mentorship. Seminar paper required. Not open to students with credit in UNIV/HNRS 391. 4 lectures.",
  "units": "4",
  "prerequisites": "Consent of instructor, and senior or graduate standing",
  "corequisites": "GE Area D5",
  "crnc": false
}